opsys_temperature_logger/__init__.py
opsys_temperature_logger/tc08usb.py
opsys_temperature_logger/temperature_logger.py
opsys_temperature_logger/temperature_logger_abstract.py
opsys_temperature_logger/usbtc08.dll
opsys_temperature_logger-0.0.2.dist-info/LICENSE
opsys_temperature_logger-0.0.2.dist-info/METADATA
opsys_temperature_logger-0.0.2.dist-info/WHEEL
opsys_temperature_logger-0.0.2.dist-info/top_level.txt
opsys_temperature_logger-0.0.2.dist-info/RECORD
